dosage-3.2.dist-info/licenses/COPYING
dosagelib/__init__.py
dosagelib/cmd.py
dosagelib/comic.py
dosagelib/configuration.py
dosagelib/director.py
dosagelib/events.py
dosagelib/helpers.py
dosagelib/http.py
dosagelib/languages.py
dosagelib/loader.py
dosagelib/logext.py
dosagelib/output.py
dosagelib/rss.py
dosagelib/scraper.py
dosagelib/singleton.py
dosagelib/updater.py
dosagelib/util.py
dosagelib/xml.py
dosagelib/__pyinstaller/__init__.py
dosagelib/__pyinstaller/hook-dosagelib.py
dosagelib/data/__init__.py
dosagelib/plugins/__init__.py
dosagelib/plugins/a.py
dosagelib/plugins/arcamax.py
dosagelib/plugins/b.py
dosagelib/plugins/c.py
dosagelib/plugins/clonemanga.py
dosagelib/plugins/comicfury.py
dosagelib/plugins/comicgenesis.py
dosagelib/plugins/comicskingdom.py
dosagelib/plugins/common.py
dosagelib/plugins/creators.py
dosagelib/plugins/d.py
dosagelib/plugins/derideal.py
dosagelib/plugins/dmfa.py
dosagelib/plugins/e.py
dosagelib/plugins/f.py
dosagelib/plugins/flowerlark.py
dosagelib/plugins/footloosecomic.py
dosagelib/plugins/g.py
dosagelib/plugins/gocomics.py
dosagelib/plugins/h.py
dosagelib/plugins/i.py
dosagelib/plugins/j.py
dosagelib/plugins/k.py
dosagelib/plugins/keenspot.py
dosagelib/plugins/kemonocafe.py
dosagelib/plugins/krisstraub.py
dosagelib/plugins/l.py
dosagelib/plugins/m.py
dosagelib/plugins/mangadex.py
dosagelib/plugins/n.py
dosagelib/plugins/namirdeiter.py
dosagelib/plugins/nitrocosm.py
dosagelib/plugins/nuklearpower.py
dosagelib/plugins/num.py
dosagelib/plugins/o.py
dosagelib/plugins/old.py
dosagelib/plugins/p.py
dosagelib/plugins/petitesymphony.py
dosagelib/plugins/projectfuture.py
dosagelib/plugins/q.py
dosagelib/plugins/r.py
dosagelib/plugins/rhjunior.py
dosagelib/plugins/rickgriffinstudios.py
dosagelib/plugins/s.py
dosagelib/plugins/sandraandwoo.py
dosagelib/plugins/shivaestudios.py
dosagelib/plugins/snafu.py
dosagelib/plugins/t.py
dosagelib/plugins/tapas.py
dosagelib/plugins/u.py
dosagelib/plugins/v.py
dosagelib/plugins/w.py
dosagelib/plugins/webcomicfactory.py
dosage-3.2.dist-info/METADATA
dosage-3.2.dist-info/WHEEL
dosage-3.2.dist-info/entry_points.txt
dosage-3.2.dist-info/top_level.txt
dosage-3.2.dist-info/RECORD
