Metadata-Version: 2.4
Name: dosage
Version: 3.2
Summary: a comic strip downloader and archiver
Maintainer-email: Tobias Gruetzmacher <tobias-dosage@23.gs>
License: MIT License
Project-URL: Homepage, https://dosage.rocks
Project-URL: Code, https://github.com/webcomics/dosage
Project-URL: Issue tracker, https://github.com/webcomics/dosage/issues
Keywords: archiver,comic,crawler,downloader,webcomic
Platform: Any
Classifier: Development Status :: 5 - Production/Stable
Classifier: Environment :: Console
Classifier: Intended Audience :: End Users/Desktop
Classifier: Operating System :: OS Independent
Classifier: Programming Language :: Python
Classifier: Programming Language :: Python :: 3 :: Only
Classifier: Programming Language :: Python :: 3.8
Classifier: Programming Language :: Python :: 3.9
Classifier: Programming Language :: Python :: 3.10
Classifier: Programming Language :: Python :: 3.11
Classifier: Programming Language :: Python :: 3.12
Classifier: Programming Language :: Python :: 3.13
Classifier: Programming Language :: Python :: 3.14
Classifier: Topic :: Internet :: WWW/HTTP
Classifier: Topic :: Multimedia :: Graphics
Requires-Python: >=3.8
License-File: COPYING
Requires-Dist: imagesize
Requires-Dist: importlib-resources>=5; python_version < "3.9"
Requires-Dist: lxml>=4
Requires-Dist: platformdirs
Requires-Dist: requests>=2
Requires-Dist: rich
Provides-Extra: bash
Requires-Dist: argcomplete; extra == "bash"
Provides-Extra: compression
Requires-Dist: brotli; platform_python_implementation == "CPython" and extra == "compression"
Requires-Dist: brotlicffi; platform_python_implementation != "CPython" and extra == "compression"
Requires-Dist: zstandard; python_version < "3.14" and extra == "compression"
Provides-Extra: dev
Requires-Dist: allure-pytest; extra == "dev"
Requires-Dist: pytest-cov; extra == "dev"
Requires-Dist: pytest-xdist; extra == "dev"
Requires-Dist: responses; extra == "dev"
Dynamic: license-file
